aqualogic/__init__.py
aqualogic/__version__.py
aqualogic/cli.py
aqualogic/core.py
aqualogic-0.1.dist-info/DESCRIPTION.rst
aqualogic-0.1.dist-info/METADATA
aqualogic-0.1.dist-info/RECORD
aqualogic-0.1.dist-info/WHEEL
aqualogic-0.1.dist-info/metadata.json
aqualogic-0.1.dist-info/top_level.txt
