Metadata-Version: 2.0
Name: aqualogic
Version: 0.1
Summary: Library for interfacing with a Hayward/Goldline AquaLogic/ProLogic pool controller.
Home-page: https://github.com/swilson/aqualogic
Author: Sean Wilson
Author-email: sean.wilson@live.ca
License: MIT
Download-URL: https://github.com/swilson/aqualogic/archive/0.1.tar.gz
Platform: UNKNOWN
Classifier: Development Status :: 4 - Beta
Classifier: Intended Audience :: Developers
Classifier: Topic :: Software Development :: Embedded Systems
Classifier: License :: OSI Approved :: MIT License
Classifier: Programming Language :: Python :: 3
Classifier: Programming Language :: Python :: 3.2
Classifier: Programming Language :: Python :: 3.3
Classifier: Programming Language :: Python :: 3.4
Requires-Dist: zope.event (>=4.3)
